apt_soso/__init__.py
apt_soso/__main__.py
apt_soso-1.0.1.dist-info/LICENSE
apt_soso-1.0.1.dist-info/WHEEL
apt_soso-1.0.1.dist-info/METADATA
apt_soso-1.0.1.dist-info/RECORD
