Metadata-Version: 2.1
Name: apt_soso
Version: 1.0.1
Summary: Provides a couple of nice-to-have commands which are not available in the standard apt suite.
Author-email: Leon Dionne <ldionne@dridesign.sh.cn>
Classifier: License :: OSI Approved :: GNU General Public License v3 or later (GPLv3+)
Classifier: Environment :: Console
Classifier: Operating System :: POSIX :: Linux
Classifier: Topic :: System :: Installation/Setup
Project-URL: Home, https://github.com/Zen-Master-SoSo/apt_soso
